tree_utils/__init__.py
tree_utils/fs_recursion.py
tree_utils/tree_recursion.py
recurse_tree_process-0.0.2.dist-info/LICENSE.txt
recurse_tree_process-0.0.2.dist-info/METADATA
recurse_tree_process-0.0.2.dist-info/WHEEL
recurse_tree_process-0.0.2.dist-info/top_level.txt
recurse_tree_process-0.0.2.dist-info/RECORD
